devtools_url_encoder/__init__.py
devtools_url_encoder-1.0.1.dist-info/METADATA
devtools_url_encoder-1.0.1.dist-info/WHEEL
devtools_url_encoder-1.0.1.dist-info/top_level.txt
devtools_url_encoder-1.0.1.dist-info/RECORD
