Metadata-Version: 2.1
Name: devtools-url-encoder
Version: 1.0.1
Summary: URL encoder/decoder
Home-page: https://devtools.at/tools/url-encoder
Author: DevTools.at
Author-email: hello@devtools.at
Project-URL: Homepage, https://devtools.at/tools/url-encoder
Project-URL: Repository, https://github.com/devtools-at/url-encoder
Classifier: Development Status :: 4 - Beta
Classifier: Intended Audience :: Developers
Classifier: License :: OSI Approved :: MIT License
Classifier: Programming Language :: Python :: 3
Requires-Python: >=3.8
